madblocks/__init__.py
madblocks/mbaws.py
madblocks/mbcloud.py
madblocks/mbibm.py
madblocks/mbmail.py
madblocks/mbotp.py
madblocks/thingspeak.py
madblocks-0.2.dist-info/METADATA
madblocks-0.2.dist-info/WHEEL
madblocks-0.2.dist-info/top_level.txt
madblocks-0.2.dist-info/RECORD
