Metadata-Version: 2.1
Name: madblocks
Version: 0.2
Summary: madBlocks Cloud Library
Home-page: https://upload.pypi.org/legacy/
Author: Surya Kumar V
Author-email: orl.suryakumar@gmail.com
License: MIT
Platform: UNKNOWN
